libsgd/__init__.py
libsgd/_sgd.py
libsgd/sgd.py
libsgd/libs/py311/_sgd.pyd
libsgd-0.17.1.dist-info/LICENSE
libsgd-0.17.1.dist-info/METADATA
libsgd-0.17.1.dist-info/WHEEL
libsgd-0.17.1.dist-info/top_level.txt
libsgd-0.17.1.dist-info/RECORD
